heartcrm/__init__.py
heartcrm/cli.py
heartcrm/conf.py
heartcrm/heart.py
heartcrm-0.1.0.dist-info/LICENSE
heartcrm-0.1.0.dist-info/METADATA
heartcrm-0.1.0.dist-info/WHEEL
heartcrm-0.1.0.dist-info/entry_points.txt
heartcrm-0.1.0.dist-info/top_level.txt
heartcrm-0.1.0.dist-info/RECORD
